{
  "root": "ʔxl",
  "etymology": {
    "etymons": [
      {
        "source": "MEA",
        "source_root": "ʔkl",
        "reference": "SL 41",
        "meaning": "to eat; to consume"
      }
    ]
  },
  "cross_reference": null,
  "stems": [
    {
      "forms": [
        "xile",
        "oxal"
      ],
      "conjugations": {
        "Preterit": [
          {
            "turoyo": ") axəl; 712; xīl; 710;",
            "translations": [],
            "references": []
          }
        ],
        "Infectum": [
          {
            "turoyo": ") iḏa d-mətxəl u=baṣrayḏe, gəd-omər disa...",
            "translations": [
              "wenn das Fleisch (des Vogels) essbar ist, sagt er..."
            ],
            "references": [
              "713",
              "94/438"
            ]
          },
          {
            "turoyo": "u=bačək lə=k-mətxəl yaliniz l-u=săwāl k-obi-le",
            "translations": [
              "‘Black millet is not eaten (by humans), people give it only to cattle’ 94/67"
            ],
            "references": []
          }
        ],
        "Infectum-wa": [
          {
            "turoyo": ") mbašal-wo u=baṣro ʕal i=nuro, sám-wo-le kăbāb, w-aḥna uxlína-wo. qaṭʕiyan l-úxal-wo aʕmayna",
            "translations": [
              "er machte uns dann immer das Fleisch auf dem Feuer zurecht, briet es und wir assen. Aber er ass niemals mit uns"
            ],
            "references": [
              "709",
              "11/248"
            ]
          },
          {
            "turoyo": "-249; xuzi hul šwaʕ=əšne ḥrene i=kurf-ayo uxlo-wa af=faruxayḏi, w lə=ṭəlbat-wa i=ṭalabiy-aṯe mini",
            "translations": [
              "ach, wenn doch diese Schlange noch sieben Jahre lang meine Jungen frässe und du mich nicht um das bitten würdest!"
            ],
            "references": [
              "709",
              "52/34"
            ]
          },
          {
            "turoyo": "i=ʕade: an=niše l=uxli-wa ʕam ag=gawre",
            "translations": [
              "‘[There was] a custom: women would not eat together with men’; 44/59;"
            ],
            "references": [
              "5"
            ]
          },
          {
            "turoyo": ") l-oxal-wa aʕli hawxa səmxu",
            "translations": [
              "ich war es nicht wert, dass ihr dies (alles) getan habt"
            ],
            "references": [
              "6"
            ]
          },
          {
            "turoyo": ") xwazi kul ənsān xud hani oxal-wa i=dawl-ayḏe hawxa b-raḥati w-i=taʕb-ayḏe",
            "translations": [
              "könnte doch jeder Mensch so wie diese (Familie) problemlos von seiner Arbeit und Mühen leben!"
            ],
            "references": [
              "LB 239"
            ]
          }
        ],
        "Imperative": [
          {
            "turoyo": ") manḥatte əšmo d-zaytune w kibe qaṣyo d-laḥmo w mərre: “xul!”",
            "translations": [
              "dann brachten sie etwas Oliven und ein Stück Brot und forderten mich auf zu essen"
            ],
            "references": [
              "LB 73"
            ]
          },
          {
            "turoyo": "məd w axúl gweto",
            "translations": [
              "nimm und iss Käse!"
            ],
            "references": [
              "LB 107"
            ]
          },
          {
            "turoyo": "k-ummo axúl, k-omər lo=k-oxanno",
            "translations": [
              "so oft sie ihn aufforderte zu essen, sagte er, er habe keine Lust"
            ],
            "references": [
              "711",
              "prs 86/4",
              "prs 237/9"
            ]
          },
          {
            "turoyo": "axúl w itóx l-gabi",
            "translations": [
              "iss und bleibe bei mir"
            ],
            "references": [
              "711",
              "prs 20/35",
              "prs 165/6",
              "prs 238/20"
            ]
          },
          {
            "turoyo": "axúl w lə=ṭorat mede b-u=sefoqo",
            "translations": [
              "iss und lass nichts in der Schüssel"
            ],
            "references": [
              "711",
              "44/58",
              "48/11",
              "60/282",
              "62/196"
            ]
          },
          {
            "turoyo": "səm kăram, ya păpāz afandi, w xul",
            "translations": [
              "greif zu, papas efendi, und iss"
            ],
            "references": [
              "711",
              "35/30",
              "44/62",
              "48/24",
              "75/120",
              "76/140"
            ]
          }
        ],
        "Participle_Active": [
          {
            "turoyo": "fayəš Xāngīr b-u=quṣro, mkayfo, axolo šatoyo",
            "translations": [
              "‘Xangir stayed at the castle, happy, eating and drinking’ 73/140;"
            ],
            "references": []
          }
        ],
        "Participle_Passive": [
          {
            "turoyo": "xílo-yo",
            "translations": [],
            "references": [
              "713"
            ]
          }
        ],
        "Infinitive": [
          {
            "turoyo": ") ḥurma hat izalax l-u=muklo",
            "translations": [
              "Frau, geh du zum Essen"
            ],
            "references": [
              "712",
              "69/27"
            ]
          },
          {
            "turoyo": "ánnaqla bəṯṯər m-u=ḥṣodo aw=warze g-moṭən, gə-mdayšnina b-u=muklo d-aw=warze",
            "translations": [
              "‘After the harvesting the melon plantations became ripe, and we began to feed on these plantations’ JL 7.8.1;"
            ],
            "references": []
          }
        ]
      },
      "stem": "I",
      "label_raw": "<font size=\"4\" style=\"font-size: 14pt\"><b><span style=\"background: transparent\">I:\n</span></b></font></font><font color=\"#000000\"><font size=\"4\" style=\"font-size: 14pt\"><i><b><span style=\"background: transparent\">xile/oxal</span></b></i></font></font></p>\n<p lang=\"en-GB\" class=\"western\"><br/>\n<br/>\n\n</p>\n<p lang=\"en-GB\" class=\"western\"><font color=\"#000000\"><font size=\"2\" style=\"font-size: 10pt\"><span style=\"background: transparent\">1)\nessen; 2) (</span></font></font><font color=\"#000000\"><font size=\"2\" style=\"font-size: 10pt\"><i><span style=\"background: transparent\">axile\nruḥe</span></i></font></font><font color=\"#000000\"><font size=\"2\" style=\"font-size: 10pt\"><span style=\"background: transparent\">)\ner verzehrte sich im Affekt, er wurde innerlich wütend; 3) (</span></font></font><font color=\"#000000\"><font size=\"2\" style=\"font-size: 10pt\"><i><span style=\"background: transparent\">l-i=emo\naxila yalda, u=waldayḏa</span></i></font></font><font color=\"#000000\"><font size=\"2\" style=\"font-size: 10pt\"><span style=\"background: transparent\">)\nes gab einen grossen Trubel, ein grosses Gedränge, Streit; 4) (</span></font></font><font color=\"#000000\"><font size=\"2\" style=\"font-size: 10pt\"><i><span style=\"background: transparent\">axile\nqar</span></i></font></font><font color=\"#000000\"><font size=\"2\" style=\"font-size: 10pt\"><i><span style=\"background: transparent\">ʕ</span></i></font></font><font color=\"#000000\"><font size=\"2\" style=\"font-size: 10pt\"><i><span style=\"background: transparent\">e\nd-u=babo</span></i></font></font><font color=\"#000000\"><font size=\"2\" style=\"font-size: 10pt\"><span style=\"background: transparent\">)\ner hat den Vater ins Grab gebracht (so sagt man etwa von einem\nUnglückskind, das gerade geboren wurde, als der Vater starb); 5)\n(</span></font></font><font color=\"#000000\"><font size=\"2\" style=\"font-size: 10pt\"><i><span style=\"background: transparent\">k-o</span></i></font></font><font color=\"#000000\"><font size=\"2\" style=\"font-size: 10pt\"><i><span style=\"background: transparent\">xəl\naʕ</span></i></font></font><font color=\"#000000\"><font size=\"2\" style=\"font-size: 10pt\"><i><span style=\"background: transparent\">le</span></i></font></font><font color=\"#000000\"><font size=\"2\" style=\"font-size: 10pt\"><span style=\"background: transparent\">)\ner passt für ihn, er verdient; er ist wert; </span></font></font><font size=\"2\" style=\"font-size: 10pt\"><span style=\"background: transparent\">6)\nLebensunterhalt bekommen; 7) verzehren, für das Essen ausgeben\n(съесть, проесть деньги, т.е. потратить\nих на еду)</span></font></p>",
      "label_gloss_tokens": [
        {
          "italic": false,
          "text": "I:\n"
        },
        {
          "italic": false,
          "text": "1)\nessen; 2) ("
        },
        {
          "italic": true,
          "text": "axile\nruḥe"
        },
        {
          "italic": false,
          "text": ")\ner verzehrte sich im Affekt, er wurde innerlich wütend; 3) ("
        },
        {
          "italic": true,
          "text": "l-i=emo\naxila yalda, u=waldayḏa"
        },
        {
          "italic": false,
          "text": ")\nes gab einen grossen Trubel, ein grosses Gedränge, Streit; 4) ("
        },
        {
          "italic": true,
          "text": "axile\nqar"
        },
        {
          "italic": true,
          "text": "ʕ"
        },
        {
          "italic": true,
          "text": "e\nd-u=babo"
        },
        {
          "italic": false,
          "text": ")\ner hat den Vater ins Grab gebracht (so sagt man etwa von einem\nUnglückskind, das gerade geboren wurde, als der Vater starb); 5)\n("
        },
        {
          "italic": true,
          "text": "k-o"
        },
        {
          "italic": true,
          "text": "xəl\naʕ"
        },
        {
          "italic": true,
          "text": "le"
        },
        {
          "italic": false,
          "text": ")\ner passt für ihn, er verdient; er ist wert; "
        },
        {
          "italic": false,
          "text": "6)\nLebensunterhalt bekommen; 7) verzehren, für das Essen ausgeben\n(съесть, проесть деньги, т.е. потратить\nих на еду)"
        }
      ]
    },
    {
      "forms": [
        "mawkele",
        "mawkəl(mawke)"
      ],
      "conjugations": {
        "Preterit": [
          {
            "turoyo": "mawkele; 713; mokele; 715; kalino b-tarʕo d-bayto, ḥḏo barṯo aṯyo, manḥátla-li w-mašḥánla-li w-mokela-li",
            "translations": [
              "‘I stopped by the door of a house, and a girl came outside, pulled me down (from the horse), warmed me and fed me’ LuF 282/30;"
            ],
            "references": []
          }
        ],
        "Infectum": [
          {
            "turoyo": "k-mitawkəl",
            "translations": [
              "man kann es zu fressen geben"
            ],
            "references": [
              "721"
            ]
          }
        ],
        "Infectum-wa": [
          {
            "turoyo": "ŭno hud kət-wi ǧŭwān mawkál-wo-li mori w mašté-wo-li",
            "translations": [
              "solange ich jung war, hat mir mein Herr zu essen und zu trinken gegeben"
            ],
            "references": [
              "719",
              "prs 213/35"
            ]
          },
          {
            "turoyo": "hiya-ze leba fayəš-wa m-u=abro həngi məqqa d-saymo-wa lo=saymo-wa lo=qoyam-wa l=əzze-wa lo=šoġal-wa hiya faqərto əzza-wa šuġlo-wa w-məklo-wayle",
            "translations": [
              "‘Her heart had been filled with grief because of her son. No matter what she did he would not get up and go to work. She (on the other hand), poor thing, would go and work and would feed him’ 77/73-74;"
            ],
            "references": []
          }
        ],
        "Imperative": [
          {
            "turoyo": "i=naʕam-aṯe-ze haw bolux aʕla mokel-a w-mnaḏ̣ef-a w-sum-a",
            "translations": [
              "‘Take care of this ostrich as well. Feed it, clean it and look after it’ 81/59 [MT];"
            ],
            "references": []
          }
        ],
        "Infinitive": [
          {
            "turoyo": "tukilo; tawkilo; tawkolo",
            "translations": [],
            "references": [
              "721"
            ]
          }
        ]
      },
      "stem": "III",
      "label_raw": "<font size=\"4\" style=\"font-size: 14pt\"><b><span style=\"background: transparent\">III:\n</span></b></font></font><font color=\"#000000\"><font size=\"4\" style=\"font-size: 14pt\"><i><b><span style=\"background: transparent\">mawkele/mawkəl(mawke)</span></b></i></font></font></p>\n<p lang=\"en-GB\" class=\"western\"><span style=\"background: transparent\">essen\nlassen;</span></p>",
      "label_gloss_tokens": [
        {
          "italic": false,
          "text": "III:\n"
        },
        {
          "italic": false,
          "text": "essen\nlassen;"
        }
      ]
    },
    {
      "forms": [],
      "conjugations": {
        "Preterit": [
          {
            "turoyo": "mawkele; 713; mokele; 715; kalino b-tarʕo d-bayto, ḥḏo barṯo aṯyo, manḥátla-li w-mašḥánla-li w-mokela-li",
            "translations": [
              "‘I stopped by the door of a house, and a girl came outside, pulled me down (from the horse), warmed me and fed me’ LuF 282/30;"
            ],
            "references": []
          }
        ],
        "Infectum": [
          {
            "turoyo": "k-mitawkəl",
            "translations": [
              "man kann es zu fressen geben"
            ],
            "references": [
              "721"
            ]
          }
        ],
        "Participle_Passive": [
          {
            "turoyo": "xílo-yo",
            "translations": [],
            "references": [
              "713"
            ]
          }
        ],
        "Infinitive": [
          {
            "turoyo": "tukilo; tawkilo; tawkolo",
            "translations": [],
            "references": [
              "721"
            ]
          }
        ],
        "Infectum-wa": [
          {
            "turoyo": "ŭno hud kət-wi ǧŭwān mawkál-wo-li mori w mašté-wo-li",
            "translations": [
              "solange ich jung war, hat mir mein Herr zu essen und zu trinken gegeben"
            ],
            "references": [
              "719",
              "prs 213/35"
            ]
          },
          {
            "turoyo": "hiya-ze leba fayəš-wa m-u=abro həngi məqqa d-saymo-wa lo=saymo-wa lo=qoyam-wa l=əzze-wa lo=šoġal-wa hiya faqərto əzza-wa šuġlo-wa w-məklo-wayle",
            "translations": [
              "‘Her heart had been filled with grief because of her son. No matter what she did he would not get up and go to work. She (on the other hand), poor thing, would go and work and would feed him’ 77/73-74;"
            ],
            "references": []
          }
        ],
        "Imperative": [
          {
            "turoyo": "i=naʕam-aṯe-ze haw bolux aʕla mokel-a w-mnaḏ̣ef-a w-sum-a",
            "translations": [
              "‘Take care of this ostrich as well. Feed it, clean it and look after it’ 81/59 [MT];"
            ],
            "references": []
          }
        ]
      },
      "stem": "Detransitive"
    }
  ],
  "uncertain": false,
  "lemma_header_raw": "<p lang=\"en-GB\" class=\"western\"><font color=\"#000000\"><span style=\"background: transparent\">ʔxl</span></font><font color=\"#000000\"><font size=\"2\" style=\"font-size: 11pt\"><i><span style=\"background: transparent\">\n(&lt; MEA ʔkl cf. SL 41: to eat; to consume;)</span></i></font></font></p>\n<p lang=\"en-GB\" class=\"western\"><font color=\"#000000\">",
  "lemma_header_tokens": [
    {
      "italic": false,
      "text": "ʔxl"
    },
    {
      "italic": true,
      "text": "\n(< MEA ʔkl cf. SL 41: to eat; to consume;)"
    }
  ]
}