{
  "root": "ṭrf",
  "etymology": {
    "etymons": [
      {
        "source": "MEA",
        "source_root": "ṭrp",
        "reference": "SL 555",
        "meaning": "to knock, dash"
      },
      {
        "source": "MEA",
        "source_root": "ṭrp",
        "reference": "SL 555",
        "meaning": "to trim, prune trees; 194",
        "stem": "Pa."
      }
    ]
  },
  "cross_reference": null,
  "stems": [
    {
      "forms": [
        "ṭrəfle",
        "ṭorəf"
      ],
      "conjugations": {
        "Preterit": [
          {
            "turoyo": "ṭrəfle ʕayni",
            "translations": [
              "er hat mir etwas ins Auge gestossen"
            ],
            "references": [
              "71"
            ]
          }
        ]
      },
      "stem": "I",
      "label_raw": "<font size=\"4\" style=\"font-size: 14pt\"><b><span style=\"background: transparent\">I:\n</span></b></font></font><font color=\"#000000\"><font size=\"4\" style=\"font-size: 14pt\"><i><b><span style=\"background: transparent\">ṭrəfle/ṭorəf</span></b></i></font></font></p>\n<p lang=\"en-GB\" class=\"western\"><span style=\"background: transparent\">stossen;</span></p>",
      "label_gloss_tokens": [
        {
          "italic": false,
          "text": "I:\n"
        },
        {
          "italic": false,
          "text": "stossen;"
        }
      ]
    },
    {
      "forms": [
        "mṭarafle",
        "mṭarəf"
      ],
      "conjugations": {},
      "stem": "II",
      "label_raw": "<font size=\"4\" style=\"font-size: 14pt\"><b><span style=\"background: transparent\">II:\n</span></b></font></font><font color=\"#000000\"><font size=\"4\" style=\"font-size: 14pt\"><i><b><span style=\"background: transparent\">mṭarafle/mṭarəf</span></b></i></font></font></p>\n<p lang=\"en-GB\" class=\"western\"><font color=\"#000000\"><font size=\"2\" style=\"font-size: 10pt\"><span style=\"background: transparent\">die\nHaare schneiden; НЕТ ПРИМЕРОВ</span></font></font></p>",
      "label_gloss_tokens": [
        {
          "italic": false,
          "text": "II:\n"
        },
        {
          "italic": false,
          "text": "die\nHaare schneiden; НЕТ ПРИМЕРОВ"
        }
      ]
    }
  ],
  "uncertain": false,
  "lemma_header_raw": "<p lang=\"en-GB\" class=\"western\"><font color=\"#000000\"><span style=\"background: transparent\">ṭrf</span></font><font color=\"#000000\"><font size=\"2\" style=\"font-size: 11pt\"><i><span style=\"background: transparent\">\n(&lt; MEA ṭrp cf. SL 555: to knock, dash; &lt; MEA ṭrp (Pa.) cf.\nSL 555: to trim, prune trees; 194;)</span></i></font></font></p>\n<p lang=\"en-GB\" class=\"western\"><font color=\"#000000\">",
  "lemma_header_tokens": [
    {
      "italic": false,
      "text": "ṭrf"
    },
    {
      "italic": true,
      "text": "\n(< MEA ṭrp cf. SL 555: to knock, dash; < MEA ṭrp (Pa.) cf.\nSL 555: to trim, prune trees; 194;)"
    }
  ]
}