{
  "root": "ʕr",
  "etymology": {
    "source": "Arb.",
    "notes": "ʕrǧ ‘lahm sein, lahmen, hinken, humpeln’ Wehr 826"
  },
  "cross_reference": null,
  "stems": [
    {
      "forms": [
        "mʕaražle",
        "mʕarəž",
        "mʕaraǧle",
        "mʕarəǧ"
      ],
      "conjugations": {
        "Infectum": [
          {
            "turoyo": "gd-əṯyo emo d-aryo raġla qəṣto-yo ko-mhalxo ko-mʕaržo me-raġla",
            "translations": [
              "‘Then a mother lion shall come, her foot is swollen. She limps on her foot (while) she walks’ 75/283;"
            ],
            "references": [
              "29"
            ]
          },
          {
            "turoyo": "I=bruske nayiḥo. Eló balé ṣaqaṭ yo. Ṣaqaṭ yo, komaʕrəǧ b ḥḏo raġlo.",
            "translations": [],
            "references": []
          },
          {
            "turoyo": "The pain receded. But he became lame, we was limping with one of his legs",
            "translations": [],
            "references": [
              "Sultan_Nisane"
            ]
          }
        ]
      },
      "stem": "II",
      "label_raw": "<font size=\"4\" style=\"font-size: 14pt\"><b><span style=\"background: transparent\">II:\n</span></b></font></font><font color=\"#000000\"><font size=\"4\" style=\"font-size: 14pt\"><i><b><span style=\"background: transparent\">mʕaražle/mʕarəž/\nmʕaraǧle/mʕarəǧ</span></b></i></font></font></p>\n<p lang=\"en-GB\" class=\"western\"><span style=\"background: transparent\">to\nlimp</span></p>",
      "label_gloss_tokens": [
        {
          "italic": false,
          "text": "II:\n"
        },
        {
          "italic": false,
          "text": "to\nlimp"
        }
      ]
    }
  ],
  "uncertain": false,
  "lemma_header_raw": "<p lang=\"en-GB\" class=\"western\"><font color=\"#000000\"><span style=\"background: transparent\">ʕr</span></font><font color=\"#000000\"><font size=\"2\" style=\"font-size: 11pt\"><span style=\"background: transparent\">ž\n</span></font></font><font color=\"#000000\"><font size=\"2\" style=\"font-size: 11pt\"><i><span style=\"background: transparent\">(&lt;\nArb. ʕrǧ ‘lahm sein, lahmen, hinken, humpeln’ Wehr 826)</span></i></font></font></p>\n<p lang=\"en-GB\" class=\"western\"><font color=\"#000000\">",
  "lemma_header_tokens": [
    {
      "italic": false,
      "text": "ʕr"
    },
    {
      "italic": false,
      "text": "ž\n"
    },
    {
      "italic": true,
      "text": "(<\nArb. ʕrǧ ‘lahm sein, lahmen, hinken, humpeln’ Wehr 826)"
    }
  ]
}