{
  "root": "ḏ̣ḥy",
  "etymology": {
    "etymons": [
      {
        "source": "Arab.",
        "source_root": "ḍḥy",
        "reference": "Wehr 743",
        "meaning": "opfern, als Opfer darbringen"
      }
    ]
  },
  "root_gloss": null,
  "cross_reference": null,
  "stems": [
    {
      "stem": "II",
      "forms": ["mḏ̣aḥele", "mḏ̣aḥe"],
      "conjugations": {
        "Infectum": [
          {
            "turoyo": "ayna mənxu gə-mḏ̣aḥe b-nafše",
            "translations": ["wer von euch wird sich aufopfern?"],
            "references": ["419"],
            "tokens": [
              {
                "kind": "turoyo",
                "value": "ayna mənxu gə-mḏ̣aḥe b-nafše "
              },
              {
                "kind": "translation",
                "value": "ʻwer von euch wird sich aufopfern?ʼ"
              },
              {
                "kind": "punct",
                "value": ";"
              },
              {
                "kind": "turoyo",
                "value": " "
              },
              {
                "kind": "ref",
                "value": "419"
              },
              {
                "kind": "punct",
                "value": ";"
              }
            ],
            "text": "ayna mənxu gə-mḏ̣aḥe b-nafše ʻwer von euch wird sich aufopfern?ʼ; 419;"
          }
        ]
      },
      "label_gloss_tokens": [
        {
          "italic": false,
          "text": "aufopfern;"
        }
      ]
    }
  ],
  "idioms": null
}
