{
  "root": "qlf",
  "etymology": {
    "etymons": [
      {
        "source": "MEA",
        "source_root": "qlp",
        "reference": "SL 1374",
        "meaning": "to peel; to strip off the covering; to scrape off; 188"
      }
    ]
  },
  "cross_reference": null,
  "stems": [
    {
      "stem": "I",
      "forms": [
        "qləfle",
        "qoləf"
      ],
      "conjugations": {}
    },
    {
      "stem": "Detransitive",
      "forms": [],
      "conjugations": {
        "Preterit": [
          {
            "text": "hul arbaʕ w-ʕəsri saʕat qlif u=garw-awo w-qlif u=ǧídariy-awo mene w-nayəḥ-le ‘innerhalb von 24 Stunden schälten sich die Pocken von ihm ab und er wurde gesund’; 30/23 [LTN] [MT]",
            "turoyo": "",
            "translations": [],
            "references": []
          }
        ],
        "Infectum": [
          {
            "text": "bəṯṯər b-tarte=saʕayat ko-mikalpət, yaʕni i=qlaft-ayḏe ko-məqlofo ʻnach zwei Stunden schält sich (der Weizen) aus, d.h. die Schale trennt sich von ihm abʼ; 94/251;",
            "turoyo": "",
            "translations": [],
            "references": []
          }
        ]
      }
    }
  ],
  "idioms": [
    "abhäuten, schälen;",
    "sich abschälen"
  ],
  "uncertain": false
}