{
  "root": "šlq",
  "etymology": {
    "etymons": [
      {
        "source": "MEA",
        "source_root": "šlq",
        "reference": "SL 1569",
        "meaning": "to cook, boil down"
      }
    ]
  },
  "cross_reference": null,
  "stems": [
    {
      "stem": "I",
      "forms": [
        "šləqle",
        "šoləq"
      ],
      "conjugations": {
        "Preterit": [
          {
            "text": "šləqləx ḥəmṣe, k-lŭṭaʕno, lo=k-oṯe mede b-lišoni ʻdu hast Erbsen geröstet, ich lecke und bekomme nichts auf meine Zungeʼ; 69; prs 239/5;",
            "turoyo": "",
            "translations": [],
            "references": []
          }
        ],
        "Infectum": [
          {
            "text": "ab=buzarʕ-ani dəṯṯe məd-hawən qădar bardəš, ko-šəlqən-ne ʻwenn soviel Kerne zusammengekommen sind, dass sie einen Kochtopf füllen, kocht man sieʼ; 110; 94/70;",
            "turoyo": "",
            "translations": [],
            "references": []
          }
        ]
      }
    },
    {
      "stem": "Detransitive",
      "forms": [],
      "conjugations": {
        "Preterit": [
          {
            "text": "šlīq babo ʻdessen Vater gesotten werden möge!ʼ; 125;",
            "turoyo": "",
            "translations": [],
            "references": []
          }
        ],
        "Part. Pass.": [
          {
            "text": "iḏa kito, k-ŭxalno beʕe šliqe-ste ‘wenn es welche gibt, esse ich auch gesottene Eier’; 134; 9/27;",
            "turoyo": "",
            "translations": [],
            "references": []
          }
        ]
      }
    }
  ],
  "idioms": [
    "kochen, sieden, rösten;"
  ],
  "uncertain": false
}