{
  "root": "ṣwr",
  "etymology": {
    "etymons": [
      {
        "source": "MEA",
        "source_root": "ṣwr",
        "reference": "SL 1281",
        "meaning": "to adorn, paint"
      }
    ]
  },
  "cross_reference": null,
  "stems": [
    {
      "stem": "II",
      "forms": ["mṣawalle", "mṣawər"],
      "conjugations": {
        "Preterit": [
          {
            "turoyo": "ḥzeli də-mṣawro kačke, šafər m-awxa layt 472; 52/165;",
            "translations": [
              "ich sah, dass sie sich in ein Mädchen verwandelte, wie es kein schöneres gibt"
            ],
            "references": ["472; 52/165"]
          }
        ],
        "Infectum": [
          {
            "turoyo": "u=lalyo lə=ko-domax-le həngi i=zʕurt-ayo ko-miṣawro l-qul ʕayne",
            "translations": [
              "nachts kann er nicht schlafen, weil ihm das Bild des Mädchens dauernd vor Augen steht"
            ],
            "references": []
          }
        ],
        "Part. Pass.": [
          {
            "turoyo": "kəlla mṣawarto l-qul ʕayni 472; 2/18;",
            "translations": ["sie steht mir noch vor Augen"],
            "references": ["472; 2/18"]
          }
        ]
      }
    }
  ],
  "uncertain": false
}
